fs_server/__init__.py
fs_server/__main__.py
fs_server/mapping.py
fs_server-0.1.3.dist-info/METADATA
fs_server-0.1.3.dist-info/WHEEL
fs_server-0.1.3.dist-info/entry_points.txt
fs_server-0.1.3.dist-info/top_level.txt
fs_server-0.1.3.dist-info/RECORD
