Metadata-Version: 2.1
Name: fs-server
Version: 0.1.3
Summary: simple crontab implemented on thread executor pool
Home-page: https://github.com/weaming/fs_server
Author: weaming
Author-email: garden.yuen@gmail.com
License: UNKNOWN
Project-URL: Source, https://github.com/weaming/fs_server
Project-URL: Bug Reports, https://github.com/weaming/fs_server
Keywords: socks,sendfile,async,fileserver
Platform: UNKNOWN
Requires-Dist: filetree (==0.3.5)
Requires-Dist: httptools (==0.1.1)
Requires-Dist: ordereddict (==1.1)
Requires-Dist: pysendfile (==2.0.1)
